.gitignore
.travis.yml
CHANGES.rst
COPYRIGHT.txt
LICENSE.txt
MANIFEST.in
README.rst
buildout.cfg
requirements.txt
setup.py
src/cipher/__init__.py
src/cipher.encryptingstorage.egg-info/PKG-INFO
src/cipher.encryptingstorage.egg-info/SOURCES.txt
src/cipher.encryptingstorage.egg-info/dependency_links.txt
src/cipher.encryptingstorage.egg-info/namespace_packages.txt
src/cipher.encryptingstorage.egg-info/not-zip-safe
src/cipher.encryptingstorage.egg-info/requires.txt
src/cipher.encryptingstorage.egg-info/top_level.txt
src/cipher/encryptingstorage/README.txt
src/cipher/encryptingstorage/__init__.py
src/cipher/encryptingstorage/component.xml
src/cipher/encryptingstorage/encrypt_util.py
src/cipher/encryptingstorage/tests/__init__.py
src/cipher/encryptingstorage/tests/test_doc.py
src/cipher/encryptingstorage/tests/test_encrypt.py
src/cipher/encryptingstorage/tests/test_zodb.py