Metadata-Version: 1.0
Name: cipher.encryptingstorage
Version: 1.1
Summary: ZODB storage wrapper for encryption of database records
Home-page: http://pypi.python.org/pypi/cipher.encryptingstorage/
Author: Zope Foundation and Contributors
Author-email: zope-dev@zope.org
License: ZPL 2.1
Keywords: Python Zope encryption
Platform: UNKNOWN
